Metadata-Version: 2.1
Name: mysql-logger
Version: 0.0.1
Summary: A simple logger class for MySQL and MariaDB
Home-page: https://github.com/ghiandFe/MySQLLogger
Author: ghiandFe
Author-email: info.fgsoftware@gmail.com
License: MIT
Platform: UNKNOWN
Classifier: License :: OSI Approved :: MIT License
Classifier: Programming Language :: Python :: 3
Classifier: Programming Language :: Python :: 3.9
License-File: LICENSE.txt
